dnsdb.py
dnsdb_python-1.2.4.dist-info/LICENSE
dnsdb_python-1.2.4.dist-info/METADATA
dnsdb_python-1.2.4.dist-info/WHEEL
dnsdb_python-1.2.4.dist-info/entry_points.txt
dnsdb_python-1.2.4.dist-info/top_level.txt
dnsdb_python-1.2.4.dist-info/RECORD
