Metadata-Version: 2.1
Name: dnsdb-python
Version: 1.2.4
Summary: A full-featured unofficial Python client and CLI for Farsight Security's DNSDB passive DNS service
Home-page: https://domainaware.github.io/dnsdb-python/
Author: Sean Whalen
Author-email: whalenster@gmail.com
License: Apache 2.0
Keywords: DNS,passive,DNS,Farsight Security,DNSDB
Platform: UNKNOWN
Classifier: Development Status :: 5 - Production/Stable
Classifier: Intended Audience :: Developers
Classifier: Intended Audience :: Information Technology
Classifier: Operating System :: OS Independent
Classifier: License :: OSI Approved :: Apache Software License
Classifier: Programming Language :: Python :: 2
Classifier: Programming Language :: Python :: 2.7
Classifier: Programming Language :: Python :: 3
Classifier: Programming Language :: Python :: 3.0
Classifier: Programming Language :: Python :: 3.1
Classifier: Programming Language :: Python :: 3.2
Classifier: Programming Language :: Python :: 3.3
Classifier: Programming Language :: Python :: 3.4
Classifier: Programming Language :: Python :: 3.5
Classifier: Programming Language :: Python :: 3.6
Classifier: Programming Language :: Python :: 3.7
Requires-Dist: requests
Requires-Dist: python-dateutil
Requires-Dist: dateparser
Requires-Dist: click
